places_geocode/__init__.py
places_geocode/places_api.py
places_geocode-0.2.6.dist-info/METADATA
places_geocode-0.2.6.dist-info/WHEEL
places_geocode-0.2.6.dist-info/top_level.txt
places_geocode-0.2.6.dist-info/RECORD
