Metadata-Version: 2.1
Name: places-geocode
Version: 0.2.6
Summary: Package for Places Geocoding API service
Home-page: https://medium.com/p/10cc24c34505/edit
Author: Martin Mashalov
Author-email: hello@places.place
License: MIT
Keywords: python,geocoding,forward geocoding,reverse geocoding,radius loading,loading radius,autocomplete,places of interest,POI
Platform: UNKNOWN
Classifier: Development Status :: 5 - Production/Stable
Classifier: License :: Free for non-commercial use
Classifier: Intended Audience :: Information Technology
Classifier: Programming Language :: Python :: 2
Classifier: Programming Language :: Python :: 3
Classifier: Operating System :: MacOS :: MacOS X
Classifier: Operating System :: Microsoft :: Windows
Requires-Dist: pymongo
Requires-Dist: numpy
Requires-Dist: pandas
Requires-Dist: sklearn
Requires-Dist: dependency-injector
Requires-Dist: pydantic
Requires-Dist: fastapi
Requires-Dist: cython
Requires-Dist: state-machine
